maildeck/__init__.py
maildeck/__main__.py
maildeck/config.py
maildeck/deck.py
maildeck/imap.py
maildeck/maildeck.py
maildeck-0.1.5.dist-info/METADATA
maildeck-0.1.5.dist-info/WHEEL
maildeck-0.1.5.dist-info/entry_points.txt
maildeck-0.1.5.dist-info/licenses/LICENSE.txt
maildeck-0.1.5.dist-info/RECORD
