Metadata-Version: 2.3
Name: maildeck
Version: 0.1.5
Summary: Import emails into Nextcloud Deck
Author-email: "Mathis Wiehl (@fahrradflucht)" <mail-pypi@mathiswiehl.de>
License: EUPL-1.2
Requires-Python: >=3.10
